grappelli/__init__.py
grappelli/apps.py
grappelli/checks.py
grappelli/forms.py
grappelli/models.py
grappelli/settings.py
grappelli/urls.py
grappelli/urls_docs.py
grappelli/dashboard/__init__.py
grappelli/dashboard/apps.py
grappelli/dashboard/dashboards.py
grappelli/dashboard/modules.py
grappelli/dashboard/registry.py
grappelli/dashboard/utils.py
grappelli/dashboard/management/__init__.py
grappelli/dashboard/management/commands/__init__.py
grappelli/dashboard/management/commands/customdashboard.py
grappelli/dashboard/templates/admin/index.html
grappelli/dashboard/templates/grappelli/dashboard/dashboard.html
grappelli/dashboard/templates/grappelli/dashboard/dashboard.txt
grappelli/dashboard/templates/grappelli/dashboard/dummy.html
grappelli/dashboard/templates/grappelli/dashboard/module.html
grappelli/dashboard/templates/grappelli/dashboard/modules/app_list.html
grappelli/dashboard/templates/grappelli/dashboard/modules/feed.html
grappelli/dashboard/templates/grappelli/dashboard/modules/group.html
grappelli/dashboard/templates/grappelli/dashboard/modules/link_list.html
grappelli/dashboard/templates/grappelli/dashboard/modules/model_list.html
grappelli/dashboard/templates/grappelli/dashboard/modules/recent_actions.html
grappelli/dashboard/templatetags/__init__.py
grappelli/dashboard/templatetags/grp_dashboard_tags.py
grappelli/static/.DS_Store
grappelli/static/admin/js/actions.js
grappelli/static/admin/js/admin/.DS_Store
grappelli/static/admin/js/admin/DateTimeShortcuts.js
grappelli/static/admin/js/admin/RelatedObjectLookups.js
grappelli/static/grappelli/.DS_Store
grappelli/static/grappelli/images/spritesheet-1694777276.png
grappelli/static/grappelli/images/backgrounds/changelist-results.png
grappelli/static/grappelli/images/backgrounds/loading-small.gif
grappelli/static/grappelli/images/backgrounds/messagelist.png
grappelli/static/grappelli/images/backgrounds/nav-grabber.gif
grappelli/static/grappelli/images/backgrounds/ui-sortable-placeholder.png
django_grappelli-3.0.10.dist-info/LICENSE
django_grappelli-3.0.10.dist-info/METADATA
django_grappelli-3.0.10.dist-info/WHEEL
django_grappelli-3.0.10.dist-info/top_level.txt
django_grappelli-3.0.10.dist-info/RECORD
