Metadata-Version: 1.2
Name: django-grappelli
Version: 3.0.10
Summary: A jazzy skin for the Django Admin-Interface.
Home-page: http://django-grappelli.readthedocs.org
Author: Patrick Kranzlmueller, Axel Swoboda (vonautomatisch)
Author-email: office@vonautomatisch.at
License: BSD
Project-URL: Source, https://github.com/sehmaschine/django-grappelli
Platform: UNKNOWN
Classifier: Development Status :: 5 - Production/Stable
Classifier: Environment :: Web Environment
Classifier: Framework :: Django
Classifier: Intended Audience :: Developers
Classifier: License :: OSI Approved :: BSD License
Classifier: Operating System :: OS Independent
Classifier: Programming Language :: Python :: 3
Classifier: Programming Language :: Python :: 3.8
Classifier: Programming Language :: Python :: 3.9
Classifier: Programming Language :: Python :: 3.10
